smaland/__init__.py
smaland/constants.py
smaland/smaland.py
smaland/subscription_callback.py
smaland/totp.py
tests/__init__.py
tests/test_smaland.py
smaland-0.0.6.dist-info/LICENSE
smaland-0.0.6.dist-info/METADATA
smaland-0.0.6.dist-info/WHEEL
smaland-0.0.6.dist-info/top_level.txt
smaland-0.0.6.dist-info/RECORD
