Metadata-Version: 2.1
Name: smaland
Version: 0.0.6
Summary: Python Avanza API
Home-page: https://github.com/emilwareus/smaland
Author: Emil Wåreus
Author-email: emil.wareus47@gmail.com
License: UNKNOWN
Platform: UNKNOWN
Classifier: Programming Language :: Python :: 3
Classifier: License :: OSI Approved :: MIT License
Classifier: Operating System :: OS Independent
Requires-Python: >=3.6
